{
  "key": "ckprahalad2010the",
  "title": "The fortune at the bottom of the pyramid",
  "authors": [
    "C. K. Prahalad",
    "Stuart L. Hart"
  ],
  "year": 2010,
  "abstract": "",
  "methodology": "_(to be filled in)_",
  "contributions": [],
  "weaknesses": [],
  "future_works": [],
  "referenced_papers": [],
  "important_keywords": [],
  "venue": "Revista Eletrônica de Estratégia & Negócios",
  "doi": "10.19177/reen.v1e220081-23",
  "institutions": [],
  "themes": [],
  "relevance": "medium",
  "emerald_relevance": "_(auto_score=0.6446 — review and re-classify)_",
  "confidence": "medium",
  "verified": false,
  "status": "indexed",
  "search_query": "The fortune at the bottom of the pyramid",
  "notes": "This article is based on a 1998 working paper from the authors. It was originally published in Strategy+Business n. 26, first quarter 2002, and is one of the basis for the CK Prahalad best seller of the same title. Tha article argues about the possibility and opportunity to trans...",
  "source_files": [
    "research\\literature\\papers\\ckprahalad2010the.md"
  ],
  "first_seen": "2026-05-18T11:35:43.927758Z",
  "last_updated": "2026-05-18T11:35:43.937480Z"
}
