{
  "key": "tang2020shareholders",
  "title": "Do shareholders benefit from green bonds?",
  "authors": [
    "Tang, D. Y.",
    "Zhang, Y."
  ],
  "year": 2020,
  "abstract": "",
  "methodology": "",
  "contributions": [],
  "weaknesses": [],
  "future_works": [],
  "referenced_papers": [],
  "important_keywords": [
    "green-finance"
  ],
  "venue": "Journal of Corporate Finance, 61, 101427",
  "doi": "10.1016/j.jcorpfin.2018.12.001",
  "institutions": [],
  "themes": [
    "green-finance"
  ],
  "relevance": "high",
  "emerald_relevance": "",
  "confidence": "low",
  "verified": true,
  "status": "stub",
  "search_query": "Tang Zhang shareholders benefit green bonds JCF 2020",
  "notes": "",
  "source_files": [],
  "first_seen": "2026-05-17T19:47:01.386196Z",
  "last_updated": "2026-05-17T19:47:01.386200Z"
}
